<?xml version="1.0" encoding="UTF-8"?>

<!-- DEFAULT MENTAL CALCULATION SHEET -->


<sheet header="" title="Converse of intercept theorem" subtitle="" text="" answers_title="Example of solutions:">

	<!-- Default values: type="std" unit="cm" font_size_offset="0" -->
	<!-- Available layout types: std|short_test|mini_test|equations|mental -->
	<layout type="std" font_size_offset="-1">
		<exc>
			<line nb="None">
				<exercises>all</exercises>
			</line>
		</exc>
		<ans>
			<line nb="None">
				<exercises>all</exercises>
			</line>
		</ans>
	</layout>

	<!-- Default values: id='generic' kind='' subkind='default' -->
	<!-- ans_variant can be 'default' or 'alternative2' only -->
	<exercise>
		<question kind="intercept_theorem_converse" subkind="triangle" ans_variant="alternative2">
			<nb source="ext_proportionality_quadruplet_11to30">1</nb>
		</question>
	</exercise>

	<exercise>
		<question kind="intercept_theorem_converse" subkind="butterfly" ans_variant="alternative2">
			<nb source="ext_proportionality_quadruplet_11to50">1</nb>
		</question>
	</exercise>

	<exercise>
		<question kind="intercept_theorem_converse" subkind="triangle" ans_variant="alternative2">
			<nb source="ext_proportionality_quadruplet_21to40">1</nb>
		</question>
	</exercise>

	<exercise>
		<question kind="intercept_theorem_converse" subkind="butterfly" ans_variant="alternative2">
			<nb source="ext_proportionality_quadruplet_31to50">1</nb>
		</question>
	</exercise>

</sheet>
